LICENSE
MANIFEST.in
README.rst
setup.cfg
setup.py
graphpca/__init__.py
graphpca.egg-info/PKG-INFO
graphpca.egg-info/SOURCES.txt
graphpca.egg-info/dependency_links.txt
graphpca.egg-info/requires.txt
graphpca.egg-info/top_level.txt
test/test_graphpca.py