Metadata-Version: 2.1
Name: graphpca
Version: 0.6
Summary: Produces a low-dimensional representation of the input graph
Home-page: https://github.com/brandones/graphpca
Author: Brandon Istenes
Author-email: brandonesbox@gmail.com
License: Apache License 2.0
Download-URL: https://github.com/brandones/graphpca/tarball/0.5
Keywords: graph,draw,pca,data,reduction,dimension,compression
Platform: UNKNOWN
Classifier: Development Status :: 4 - Beta
Classifier: License :: OSI Approved :: Apache Software License
